mbpy_endpoints/__init__.py
mbpy_endpoints/endpoints.py
mbpy_endpoints/environs.py
mbpy_endpoints/errors.py
mbpy_endpoints/generators.py
mbpy_endpoints/mock.py
mbpy_endpoints/utils.py
mbpy_endpoints-0.1.2.dist-info/LICENSE
mbpy_endpoints-0.1.2.dist-info/WHEEL
mbpy_endpoints-0.1.2.dist-info/METADATA
mbpy_endpoints-0.1.2.dist-info/RECORD
