Metadata-Version: 2.1
Name: mbpy-endpoints
Version: 0.1.2
Summary: 
License: MIT
Author: Adam Morris
Author-email: classroomtechtools.ctt@gmail.com
Requires-Python: >=3.10,<4.0
Classifier: License :: OSI Approved :: MIT License
Classifier: Programming Language :: Python :: 3
Classifier: Programming Language :: Python :: 3.10
Requires-Dist: rich (>=12.4.4,<13.0.0)
Requires-Dist: uplink (>=0.9.7,<0.10.0)
